yunpath/__init__.py
yunpath/patch.py
yunpath/py.typed
yunpath-0.1.1.dist-info/METADATA
yunpath-0.1.1.dist-info/WHEEL
yunpath-0.1.1.dist-info/RECORD
